instaling_client/__init__.py
instaling_client/client.py
instaling_client-0.1.2.dist-info/LICENSE
instaling_client-0.1.2.dist-info/METADATA
instaling_client-0.1.2.dist-info/WHEEL
instaling_client-0.1.2.dist-info/top_level.txt
instaling_client-0.1.2.dist-info/RECORD
