Metadata-Version: 2.2
Name: instaling-client
Version: 0.1.2
Summary: A client for automating Instaling.pl language learning sessions
Home-page: https://github.com/pingwiniu/instaling-client
Author: Julian Zientkowski
Author-email: julianzkw1@gmail.com
Classifier: Programming Language :: Python :: 3
Classifier: License :: OSI Approved :: GNU General Public License v2 (GPLv2)
Classifier: Operating System :: OS Independent
Requires-Python: >=3.6
License-File: LICENSE
Requires-Dist: requests>=2.25.0
Requires-Dist: beautifulsoup4>=4.9.0
Dynamic: author
Dynamic: author-email
Dynamic: classifier
Dynamic: description
Dynamic: description-content-type
Dynamic: home-page
Dynamic: requires-dist
Dynamic: requires-python
Dynamic: summary
